vhpi/__init__.py
vhpi/constants.py
vhpi/exceptions.py
vhpi/main.py
vhpi/utils.py
vhpi/api/__init__.py
vhpi/api/backup.py
vhpi/api/job.py
vhpi/api/logging.py
vhpi/api/main.py
vhpi/api/snapshot.py
vhpi/api/types.py
vhpi/api/validate.py
vhpi/cli/__init__.py
vhpi/cli/interface.txt
vhpi/examples/__init__.py
vhpi/examples/vhpi_cfg.yaml
vhpi-2.0.0b14.dist-info/LICENSE.txt
vhpi-2.0.0b14.dist-info/METADATA
vhpi-2.0.0b14.dist-info/WHEEL
vhpi-2.0.0b14.dist-info/entry_points.txt
vhpi-2.0.0b14.dist-info/top_level.txt
vhpi-2.0.0b14.dist-info/RECORD
