Metadata-Version: 2.1
Name: vhpi
Version: 2.0.0b14
Summary: Turn your Raspberry Pi into an independent backup module for your network. 
Home-page: https://github.com/feluxe/very_hungry_pi
Author: Felix Meyer-Wolters
Author-email: felix@meyerwolters.de
Maintainer: Felix Meyer-Wolters
Maintainer-email: felix@meyerwolters.de
License: AGPLv3
Download-URL: https://github.com/feluxe/very_hungry_pi/tarball/2.0.0-beta.14
Keywords: raspberry-pi, backup, snapshot
Platform: 
Requires-Dist: docopt
Requires-Dist: oyaml
